{"version":1,"itemId":"16693","generated_at":"2026-04-11T18:55:40.398Z","activity_days":120,"entries":[{"char_id":"22079296","name":"Catti","class_name":"Warrior","slotId":18,"slotName":"Legs","currentItemId":23913,"currentItemName":"Fierce Heraldic Greaves","itemId":16693,"itemName":"Raex's Greaves of Destruction","scoreDelta":0.028786298292902066,"isUpgrade":true,"eligible":true,"hpDelta":165,"manaDelta":0,"acDelta":70,"focusSpellName":"","deltasDetail":{"hpDelta":165,"manaDelta":0,"acDelta":70,"svAllDelta":75,"svDeltasByType":{"FR":5,"CR":5,"MR":30,"DR":5,"PR":30}}},{"char_id":"22081334","name":"Badman","class_name":"Warrior","slotId":18,"slotName":"Legs","currentItemId":7196,"currentItemName":"Grimling Tribal Legplates","itemId":16693,"itemName":"Raex's Greaves of Destruction","scoreDelta":0.028786298292902066,"isUpgrade":true,"eligible":true,"hpDelta":165,"manaDelta":0,"acDelta":70,"focusSpellName":"","deltasDetail":{"hpDelta":165,"manaDelta":0,"acDelta":70,"svAllDelta":75,"svDeltasByType":{"FR":5,"CR":5,"MR":30,"DR":5,"PR":30}}},{"char_id":"22081452","name":"Zanzibart","class_name":"Warrior","slotId":18,"slotName":"Legs","currentItemId":4410,"currentItemName":"Black Chitin Leggings","itemId":16693,"itemName":"Raex's Greaves of Destruction","scoreDelta":0.028786298292902066,"isUpgrade":true,"eligible":true,"hpDelta":165,"manaDelta":0,"acDelta":70,"focusSpellName":"","deltasDetail":{"hpDelta":165,"manaDelta":0,"acDelta":70,"svAllDelta":75,"svDeltasByType":{"FR":5,"CR":5,"MR":30,"DR":5,"PR":30}}},{"char_id":"22080750","name":"Rgrok","class_name":"Warrior","slotId":18,"slotName":"Legs","currentItemId":30555,"currentItemName":"Bone Golem Greaves","itemId":16693,"itemName":"Raex's Greaves of Destruction","scoreDelta":0.018800943396226413,"isUpgrade":true,"eligible":true,"hpDelta":120,"manaDelta":-35,"acDelta":33,"focusSpellName":"","deltasDetail":{"hpDelta":120,"manaDelta":-35,"acDelta":33,"svAllDelta":60,"svDeltasByType":{"FR":5,"CR":5,"MR":20,"DR":0,"PR":30}}},{"char_id":"22079006","name":"Swiftblade","class_name":"Warrior","slotId":18,"slotName":"Legs","currentItemId":8289,"currentItemName":"Yttrium Wrapped Leggings","itemId":16693,"itemName":"Raex's Greaves of Destruction","scoreDelta":0.014673764600179693,"isUpgrade":true,"eligible":true,"hpDelta":65,"manaDelta":-100,"acDelta":45,"focusSpellName":"","deltasDetail":{"hpDelta":65,"manaDelta":-100,"acDelta":45,"svAllDelta":35,"svDeltasByType":{"FR":5,"CR":-15,"MR":10,"DR":5,"PR":30}}},{"char_id":"22081150","name":"Sexytank","class_name":"Warrior","slotId":18,"slotName":"Legs","currentItemId":16691,"currentItemName":"Kizrak's Greaves of Battle","itemId":16693,"itemName":"Raex's Greaves of Destruction","scoreDelta":0.014471698113207546,"isUpgrade":true,"eligible":true,"hpDelta":75,"manaDelta":0,"acDelta":25,"focusSpellName":"","deltasDetail":{"hpDelta":75,"manaDelta":0,"acDelta":25,"svAllDelta":55,"svDeltasByType":{"FR":5,"CR":5,"MR":20,"DR":-5,"PR":30}}},{"char_id":"22000349","name":"Veteran","class_name":"Warrior","slotId":18,"slotName":"Legs","currentItemId":31296,"currentItemName":"Farwater Plate Greaves","itemId":16693,"itemName":"Raex's Greaves of Destruction","scoreDelta":0.01375687331536388,"isUpgrade":true,"eligible":true,"hpDelta":65,"manaDelta":-40,"acDelta":27,"focusSpellName":"","deltasDetail":{"hpDelta":65,"manaDelta":-40,"acDelta":27,"svAllDelta":51,"svDeltasByType":{"FR":5,"CR":5,"MR":30,"DR":-7,"PR":18}}},{"char_id":"22081255","name":"Rorak","class_name":"Warrior","slotId":18,"slotName":"Legs","currentItemId":28965,"currentItemName":"Leggings of Fiery Might","itemId":16693,"itemName":"Raex's Greaves of Destruction","scoreDelta":0.009630862533692719,"isUpgrade":true,"eligible":true,"hpDelta":40,"manaDelta":-75,"acDelta":35,"focusSpellName":"","deltasDetail":{"hpDelta":40,"manaDelta":-75,"acDelta":35,"svAllDelta":17,"svDeltasByType":{"FR":-25,"CR":-2,"MR":23,"DR":-2,"PR":23}}}]}