{"version":1,"itemId":"26604","generated_at":"2026-04-25T19:03:01.846Z","activity_days":120,"entries":[{"char_id":"21962923","name":"Hunted","class_name":"Magician","slotId":17,"slotName":"Chest","currentItemId":9414,"currentItemName":"Robe of the Disciple","itemId":26604,"itemName":"Koadic's Robe of Heightened Focus","scoreDelta":0.02382055817610063,"isUpgrade":true,"eligible":true,"hpDelta":120,"manaDelta":120,"acDelta":40,"focusSpellName":"","deltasDetail":{"hpDelta":120,"manaDelta":120,"acDelta":40,"svAllDelta":90,"svDeltasByType":{"FR":18,"CR":18,"MR":18,"DR":18,"PR":18}}},{"char_id":"22075587","name":"Ashes","class_name":"Wizard","slotId":17,"slotName":"Chest","currentItemId":32595,"currentItemName":"Robe of the Vampire Lord","itemId":26604,"itemName":"Koadic's Robe of Heightened Focus","scoreDelta":0.02382055817610063,"isUpgrade":true,"eligible":true,"hpDelta":120,"manaDelta":120,"acDelta":40,"focusSpellName":"","deltasDetail":{"hpDelta":120,"manaDelta":120,"acDelta":40,"svAllDelta":90,"svDeltasByType":{"FR":18,"CR":18,"MR":18,"DR":18,"PR":18}}},{"char_id":"22028951","name":"Jarienc","class_name":"Enchanter","slotId":17,"slotName":"Chest","currentItemId":32595,"currentItemName":"Robe of the Vampire Lord","itemId":26604,"itemName":"Koadic's Robe of Heightened Focus","scoreDelta":0.02382055817610063,"isUpgrade":true,"eligible":true,"hpDelta":120,"manaDelta":120,"acDelta":40,"focusSpellName":"","deltasDetail":{"hpDelta":120,"manaDelta":120,"acDelta":40,"svAllDelta":90,"svDeltasByType":{"FR":18,"CR":18,"MR":18,"DR":18,"PR":18}}},{"char_id":"22077729","name":"Aumaman","class_name":"Wizard","slotId":17,"slotName":"Chest","currentItemId":1608,"currentItemName":"Froglok Bonecaster's Robe","itemId":26604,"itemName":"Koadic's Robe of Heightened Focus","scoreDelta":0.02382055817610063,"isUpgrade":true,"eligible":true,"hpDelta":120,"manaDelta":120,"acDelta":40,"focusSpellName":"","deltasDetail":{"hpDelta":120,"manaDelta":120,"acDelta":40,"svAllDelta":90,"svDeltasByType":{"FR":18,"CR":18,"MR":18,"DR":18,"PR":18}}},{"char_id":"22077632","name":"Olorien","class_name":"Wizard","slotId":17,"slotName":"Chest","currentItemId":6858,"currentItemName":"Wily Warlock Robe","itemId":26604,"itemName":"Koadic's Robe of Heightened Focus","scoreDelta":0.02382055817610063,"isUpgrade":true,"eligible":true,"hpDelta":120,"manaDelta":120,"acDelta":40,"focusSpellName":"","deltasDetail":{"hpDelta":120,"manaDelta":120,"acDelta":40,"svAllDelta":90,"svDeltasByType":{"FR":18,"CR":18,"MR":18,"DR":18,"PR":18}}},{"char_id":"Citron","name":"Citron","class_name":"Wizard","slotId":17,"slotName":"Chest","currentItemId":24268,"currentItemName":"Woven Platinum Robe","itemId":26604,"itemName":"Koadic's Robe of Heightened Focus","scoreDelta":0.02382055817610063,"isUpgrade":true,"eligible":true,"hpDelta":120,"manaDelta":120,"acDelta":40,"focusSpellName":"","deltasDetail":{"hpDelta":120,"manaDelta":120,"acDelta":40,"svAllDelta":90,"svDeltasByType":{"FR":18,"CR":18,"MR":18,"DR":18,"PR":18}}},{"char_id":"21808677","name":"Bobn","class_name":"Wizard","slotId":17,"slotName":"Chest","currentItemId":6858,"currentItemName":"Wily Warlock Robe","itemId":26604,"itemName":"Koadic's Robe of Heightened Focus","scoreDelta":0.02382055817610063,"isUpgrade":true,"eligible":true,"hpDelta":120,"manaDelta":120,"acDelta":40,"focusSpellName":"","deltasDetail":{"hpDelta":120,"manaDelta":120,"acDelta":40,"svAllDelta":90,"svDeltasByType":{"FR":18,"CR":18,"MR":18,"DR":18,"PR":18}}},{"char_id":"22077721","name":"Barnbat","class_name":"Necromancer","slotId":17,"slotName":"Chest","currentItemId":31064,"currentItemName":"Warlock's Robe","itemId":26604,"itemName":"Koadic's Robe of Heightened Focus","scoreDelta":0.02382055817610063,"isUpgrade":true,"eligible":true,"hpDelta":120,"manaDelta":120,"acDelta":40,"focusSpellName":"","deltasDetail":{"hpDelta":120,"manaDelta":120,"acDelta":40,"svAllDelta":90,"svDeltasByType":{"FR":18,"CR":18,"MR":18,"DR":18,"PR":18}}},{"char_id":"22077722","name":"Barndoor","class_name":"Magician","slotId":17,"slotName":"Chest","currentItemId":6865,"currentItemName":"Sly Summoner's Robe","itemId":26604,"itemName":"Koadic's Robe of Heightened Focus","scoreDelta":0.02382055817610063,"isUpgrade":true,"eligible":true,"hpDelta":120,"manaDelta":120,"acDelta":40,"focusSpellName":"","deltasDetail":{"hpDelta":120,"manaDelta":120,"acDelta":40,"svAllDelta":90,"svDeltasByType":{"FR":18,"CR":18,"MR":18,"DR":18,"PR":18}}},{"char_id":"22081281","name":"Zagyre","class_name":"Necromancer","slotId":17,"slotName":"Chest","currentItemId":26129,"currentItemName":"Putrid Flesh Robe","itemId":26604,"itemName":"Koadic's Robe of Heightened Focus","scoreDelta":0.02382055817610063,"isUpgrade":true,"eligible":true,"hpDelta":120,"manaDelta":120,"acDelta":40,"focusSpellName":"","deltasDetail":{"hpDelta":120,"manaDelta":120,"acDelta":40,"svAllDelta":90,"svDeltasByType":{"FR":18,"CR":18,"MR":18,"DR":18,"PR":18}}},{"char_id":"22075966","name":"Pyrexia","class_name":"Magician","slotId":17,"slotName":"Chest","currentItemId":29127,"currentItemName":"Tserrina`s Robe","itemId":26604,"itemName":"Koadic's Robe of Heightened Focus","scoreDelta":0.02382055817610063,"isUpgrade":true,"eligible":true,"hpDelta":120,"manaDelta":120,"acDelta":40,"focusSpellName":"","deltasDetail":{"hpDelta":120,"manaDelta":120,"acDelta":40,"svAllDelta":90,"svDeltasByType":{"FR":18,"CR":18,"MR":18,"DR":18,"PR":18}}},{"char_id":"22036802","name":"Petish","class_name":"Magician","slotId":17,"slotName":"Chest","currentItemId":1644,"currentItemName":"Loam Encrusted Robe","itemId":26604,"itemName":"Koadic's Robe of Heightened Focus","scoreDelta":0.02382055817610063,"isUpgrade":true,"eligible":true,"hpDelta":120,"manaDelta":120,"acDelta":40,"focusSpellName":"","deltasDetail":{"hpDelta":120,"manaDelta":120,"acDelta":40,"svAllDelta":90,"svDeltasByType":{"FR":18,"CR":18,"MR":18,"DR":18,"PR":18}}},{"char_id":"21829645","name":"Jiva","class_name":"Wizard","slotId":17,"slotName":"Chest","currentItemId":29685,"currentItemName":"Robe of Benevolence","itemId":26604,"itemName":"Koadic's Robe of Heightened Focus","scoreDelta":0.02382055817610063,"isUpgrade":true,"eligible":true,"hpDelta":120,"manaDelta":120,"acDelta":40,"focusSpellName":"","deltasDetail":{"hpDelta":120,"manaDelta":120,"acDelta":40,"svAllDelta":90,"svDeltasByType":{"FR":18,"CR":18,"MR":18,"DR":18,"PR":18}}},{"char_id":"22081275","name":"Mabampus","class_name":"Wizard","slotId":17,"slotName":"Chest","currentItemId":1608,"currentItemName":"Froglok Bonecaster's Robe","itemId":26604,"itemName":"Koadic's Robe of Heightened Focus","scoreDelta":0.02382055817610063,"isUpgrade":true,"eligible":true,"hpDelta":120,"manaDelta":120,"acDelta":40,"focusSpellName":"","deltasDetail":{"hpDelta":120,"manaDelta":120,"acDelta":40,"svAllDelta":90,"svDeltasByType":{"FR":18,"CR":18,"MR":18,"DR":18,"PR":18}}},{"char_id":"Pugs","name":"Pugs","class_name":"Enchanter","slotId":17,"slotName":"Chest","currentItemId":26528,"currentItemName":"Bile Stained Robes","itemId":26604,"itemName":"Koadic's Robe of Heightened Focus","scoreDelta":0.02382055817610063,"isUpgrade":true,"eligible":true,"hpDelta":120,"manaDelta":120,"acDelta":40,"focusSpellName":"","deltasDetail":{"hpDelta":120,"manaDelta":120,"acDelta":40,"svAllDelta":90,"svDeltasByType":{"FR":18,"CR":18,"MR":18,"DR":18,"PR":18}}},{"char_id":"22078756","name":"Mager","class_name":"Magician","slotId":17,"slotName":"Chest","currentItemId":26528,"currentItemName":"Bile Stained Robes","itemId":26604,"itemName":"Koadic's Robe of Heightened Focus","scoreDelta":0.02382055817610063,"isUpgrade":true,"eligible":true,"hpDelta":120,"manaDelta":120,"acDelta":40,"focusSpellName":"","deltasDetail":{"hpDelta":120,"manaDelta":120,"acDelta":40,"svAllDelta":90,"svDeltasByType":{"FR":18,"CR":18,"MR":18,"DR":18,"PR":18}}},{"char_id":"Kalmic","name":"Kalmic","class_name":"Wizard","slotId":17,"slotName":"Chest","currentItemId":26528,"currentItemName":"Bile Stained Robes","itemId":26604,"itemName":"Koadic's Robe of Heightened Focus","scoreDelta":0.02382055817610063,"isUpgrade":true,"eligible":true,"hpDelta":120,"manaDelta":120,"acDelta":40,"focusSpellName":"","deltasDetail":{"hpDelta":120,"manaDelta":120,"acDelta":40,"svAllDelta":90,"svDeltasByType":{"FR":18,"CR":18,"MR":18,"DR":18,"PR":18}}},{"char_id":"22078960","name":"Romestamo","class_name":"Magician","slotId":17,"slotName":"Chest","currentItemId":6865,"currentItemName":"Sly Summoner's Robe","itemId":26604,"itemName":"Koadic's Robe of Heightened Focus","scoreDelta":0.02382055817610063,"isUpgrade":true,"eligible":true,"hpDelta":120,"manaDelta":120,"acDelta":40,"focusSpellName":"","deltasDetail":{"hpDelta":120,"manaDelta":120,"acDelta":40,"svAllDelta":90,"svDeltasByType":{"FR":18,"CR":18,"MR":18,"DR":18,"PR":18}}},{"char_id":"22081361","name":"Gondry","class_name":"Magician","slotId":17,"slotName":"Chest","currentItemId":1240,"currentItemName":"Apothic Robe","itemId":26604,"itemName":"Koadic's Robe of Heightened Focus","scoreDelta":0.02382055817610063,"isUpgrade":true,"eligible":true,"hpDelta":120,"manaDelta":120,"acDelta":40,"focusSpellName":"","deltasDetail":{"hpDelta":120,"manaDelta":120,"acDelta":40,"svAllDelta":90,"svDeltasByType":{"FR":18,"CR":18,"MR":18,"DR":18,"PR":18}}},{"char_id":"22081365","name":"Lefty","class_name":"Enchanter","slotId":17,"slotName":"Chest","currentItemId":1607,"currentItemName":"Siren Scale Robe","itemId":26604,"itemName":"Koadic's Robe of Heightened Focus","scoreDelta":0.02382055817610063,"isUpgrade":true,"eligible":true,"hpDelta":120,"manaDelta":120,"acDelta":40,"focusSpellName":"","deltasDetail":{"hpDelta":120,"manaDelta":120,"acDelta":40,"svAllDelta":90,"svDeltasByType":{"FR":18,"CR":18,"MR":18,"DR":18,"PR":18}}},{"char_id":"22034563","name":"Wish","class_name":"Enchanter","slotId":17,"slotName":"Chest","currentItemId":1606,"currentItemName":"Mana Robe","itemId":26604,"itemName":"Koadic's Robe of Heightened Focus","scoreDelta":0.02382055817610063,"isUpgrade":true,"eligible":true,"hpDelta":120,"manaDelta":120,"acDelta":40,"focusSpellName":"","deltasDetail":{"hpDelta":120,"manaDelta":120,"acDelta":40,"svAllDelta":90,"svDeltasByType":{"FR":18,"CR":18,"MR":18,"DR":18,"PR":18}}},{"char_id":"22081409","name":"Thanatos","class_name":"Necromancer","slotId":17,"slotName":"Chest","currentItemId":32595,"currentItemName":"Robe of the Vampire Lord","itemId":26604,"itemName":"Koadic's Robe of Heightened Focus","scoreDelta":0.02382055817610063,"isUpgrade":true,"eligible":true,"hpDelta":120,"manaDelta":120,"acDelta":40,"focusSpellName":"","deltasDetail":{"hpDelta":120,"manaDelta":120,"acDelta":40,"svAllDelta":90,"svDeltasByType":{"FR":18,"CR":18,"MR":18,"DR":18,"PR":18}}},{"char_id":"Enticer","name":"Enticer","class_name":"Enchanter","slotId":17,"slotName":"Chest","currentItemId":29629,"currentItemName":"Robe of Primordial Waters","itemId":26604,"itemName":"Koadic's Robe of Heightened Focus","scoreDelta":0.02382055817610063,"isUpgrade":true,"eligible":true,"hpDelta":120,"manaDelta":120,"acDelta":40,"focusSpellName":"","deltasDetail":{"hpDelta":120,"manaDelta":120,"acDelta":40,"svAllDelta":90,"svDeltasByType":{"FR":18,"CR":18,"MR":18,"DR":18,"PR":18}}},{"char_id":"22081151","name":"Buffbotgirl","class_name":"Enchanter","slotId":17,"slotName":"Chest","currentItemId":29660,"currentItemName":"Robe of Haunted Dreams","itemId":26604,"itemName":"Koadic's Robe of Heightened Focus","scoreDelta":0.02382055817610063,"isUpgrade":true,"eligible":true,"hpDelta":120,"manaDelta":120,"acDelta":40,"focusSpellName":"","deltasDetail":{"hpDelta":120,"manaDelta":120,"acDelta":40,"svAllDelta":90,"svDeltasByType":{"FR":18,"CR":18,"MR":18,"DR":18,"PR":18}}},{"char_id":"22081368","name":"Buffin","class_name":"Magician","slotId":17,"slotName":"Chest","currentItemId":14306,"currentItemName":"Gold Runed Shirt","itemId":26604,"itemName":"Koadic's Robe of Heightened Focus","scoreDelta":0.02382055817610063,"isUpgrade":true,"eligible":true,"hpDelta":120,"manaDelta":120,"acDelta":40,"focusSpellName":"","deltasDetail":{"hpDelta":120,"manaDelta":120,"acDelta":40,"svAllDelta":90,"svDeltasByType":{"FR":18,"CR":18,"MR":18,"DR":18,"PR":18}}},{"char_id":"22079007","name":"Fedora","class_name":"Magician","slotId":17,"slotName":"Chest","currentItemId":1644,"currentItemName":"Loam Encrusted Robe","itemId":26604,"itemName":"Koadic's Robe of Heightened Focus","scoreDelta":0.02382055817610063,"isUpgrade":true,"eligible":true,"hpDelta":120,"manaDelta":120,"acDelta":40,"focusSpellName":"","deltasDetail":{"hpDelta":120,"manaDelta":120,"acDelta":40,"svAllDelta":90,"svDeltasByType":{"FR":18,"CR":18,"MR":18,"DR":18,"PR":18}}},{"char_id":"22078198","name":"Kintsugi","class_name":"Enchanter","slotId":17,"slotName":"Chest","currentItemId":1608,"currentItemName":"Froglok Bonecaster's Robe","itemId":26604,"itemName":"Koadic's Robe of Heightened Focus","scoreDelta":0.02382055817610063,"isUpgrade":true,"eligible":true,"hpDelta":120,"manaDelta":120,"acDelta":40,"focusSpellName":"","deltasDetail":{"hpDelta":120,"manaDelta":120,"acDelta":40,"svAllDelta":90,"svDeltasByType":{"FR":18,"CR":18,"MR":18,"DR":18,"PR":18}}},{"char_id":"22077752","name":"Zosweet","class_name":"Enchanter","slotId":17,"slotName":"Chest","currentItemId":27883,"currentItemName":"Robe of Viscid Slime","itemId":26604,"itemName":"Koadic's Robe of Heightened Focus","scoreDelta":0.01595042256289308,"isUpgrade":true,"eligible":true,"hpDelta":70,"manaDelta":70,"acDelta":18,"focusSpellName":"","deltasDetail":{"hpDelta":70,"manaDelta":70,"acDelta":18,"svAllDelta":70,"svDeltasByType":{"FR":14,"CR":14,"MR":14,"DR":14,"PR":14}}},{"char_id":"21829644","name":"Fennin","class_name":"Wizard","slotId":17,"slotName":"Chest","currentItemId":29333,"currentItemName":"Celestial Essence Robe","itemId":26604,"itemName":"Koadic's Robe of Heightened Focus","scoreDelta":0.014198948506289307,"isUpgrade":true,"eligible":true,"hpDelta":90,"manaDelta":40,"acDelta":25,"focusSpellName":"","deltasDetail":{"hpDelta":90,"manaDelta":40,"acDelta":25,"svAllDelta":60,"svDeltasByType":{"FR":13,"CR":8,"MR":13,"DR":13,"PR":13}}},{"char_id":"21983467","name":"Druzzil","class_name":"Enchanter","slotId":17,"slotName":"Chest","currentItemId":29333,"currentItemName":"Celestial Essence Robe","itemId":26604,"itemName":"Koadic's Robe of Heightened Focus","scoreDelta":0.014198948506289307,"isUpgrade":true,"eligible":true,"hpDelta":90,"manaDelta":40,"acDelta":25,"focusSpellName":"","deltasDetail":{"hpDelta":90,"manaDelta":40,"acDelta":25,"svAllDelta":60,"svDeltasByType":{"FR":13,"CR":8,"MR":13,"DR":13,"PR":13}}},{"char_id":"Cothero","name":"Cothero","class_name":"Magician","slotId":17,"slotName":"Chest","currentItemId":29333,"currentItemName":"Celestial Essence Robe","itemId":26604,"itemName":"Koadic's Robe of Heightened Focus","scoreDelta":0.014198948506289307,"isUpgrade":true,"eligible":true,"hpDelta":90,"manaDelta":40,"acDelta":25,"focusSpellName":"","deltasDetail":{"hpDelta":90,"manaDelta":40,"acDelta":25,"svAllDelta":60,"svDeltasByType":{"FR":13,"CR":8,"MR":13,"DR":13,"PR":13}}},{"char_id":"22081399","name":"Stunkie","class_name":"Wizard","slotId":17,"slotName":"Chest","currentItemId":8497,"currentItemName":"Bile Drenched Flesh Robe","itemId":26604,"itemName":"Koadic's Robe of Heightened Focus","scoreDelta":0.011677771226415095,"isUpgrade":true,"eligible":true,"hpDelta":120,"manaDelta":40,"acDelta":-10,"focusSpellName":"","deltasDetail":{"hpDelta":120,"manaDelta":40,"acDelta":-10,"svAllDelta":40,"svDeltasByType":{"FR":8,"CR":8,"MR":8,"DR":8,"PR":8}}},{"char_id":"Creator","name":"Creator","class_name":"Magician","slotId":17,"slotName":"Chest","currentItemId":8497,"currentItemName":"Bile Drenched Flesh Robe","itemId":26604,"itemName":"Koadic's Robe of Heightened Focus","scoreDelta":0.011677771226415095,"isUpgrade":true,"eligible":true,"hpDelta":120,"manaDelta":40,"acDelta":-10,"focusSpellName":"","deltasDetail":{"hpDelta":120,"manaDelta":40,"acDelta":-10,"svAllDelta":40,"svDeltasByType":{"FR":8,"CR":8,"MR":8,"DR":8,"PR":8}}},{"char_id":"22075973","name":"Ishira","class_name":"Magician","slotId":17,"slotName":"Chest","currentItemId":31333,"currentItemName":"Ancient Wurm Hide Robe","itemId":26604,"itemName":"Koadic's Robe of Heightened Focus","scoreDelta":0.010684502751572325,"isUpgrade":true,"eligible":true,"hpDelta":120,"manaDelta":70,"acDelta":10,"focusSpellName":"","deltasDetail":{"hpDelta":120,"manaDelta":70,"acDelta":10,"svAllDelta":15,"svDeltasByType":{"FR":3,"CR":3,"MR":3,"DR":3,"PR":3}}},{"char_id":"21918666","name":"Minnec","class_name":"Necromancer","slotId":17,"slotName":"Chest","currentItemId":15785,"currentItemName":"Vorshar's Robe of the Blight","itemId":26604,"itemName":"Koadic's Robe of Heightened Focus","scoreDelta":0.009925339033018867,"isUpgrade":true,"eligible":true,"hpDelta":35,"manaDelta":25,"acDelta":25,"focusSpellName":"","deltasDetail":{"hpDelta":35,"manaDelta":25,"acDelta":25,"svAllDelta":50,"svDeltasByType":{"FR":8,"CR":8,"MR":8,"DR":8,"PR":18}}},{"char_id":"22017346","name":"Wizzie","class_name":"Wizard","slotId":17,"slotName":"Chest","currentItemId":15788,"currentItemName":"Arantir's Robe of Discovery","itemId":26604,"itemName":"Koadic's Robe of Heightened Focus","scoreDelta":0.009874557783018868,"isUpgrade":true,"eligible":true,"hpDelta":40,"manaDelta":20,"acDelta":25,"focusSpellName":"","deltasDetail":{"hpDelta":40,"manaDelta":20,"acDelta":25,"svAllDelta":50,"svDeltasByType":{"FR":10,"CR":6,"MR":12,"DR":10,"PR":12}}},{"char_id":"21829640","name":"Solusek","class_name":"Wizard","slotId":17,"slotName":"Chest","currentItemId":15788,"currentItemName":"Arantir's Robe of Discovery","itemId":26604,"itemName":"Koadic's Robe of Heightened Focus","scoreDelta":0.009874557783018868,"isUpgrade":true,"eligible":true,"hpDelta":40,"manaDelta":20,"acDelta":25,"focusSpellName":"","deltasDetail":{"hpDelta":40,"manaDelta":20,"acDelta":25,"svAllDelta":50,"svDeltasByType":{"FR":10,"CR":6,"MR":12,"DR":10,"PR":12}}},{"char_id":"22025116","name":"Mezo","class_name":"Enchanter","slotId":17,"slotName":"Chest","currentItemId":15779,"currentItemName":"Silken Augmenter's Robe","itemId":26604,"itemName":"Koadic's Robe of Heightened Focus","scoreDelta":0.009874557783018868,"isUpgrade":true,"eligible":true,"hpDelta":40,"manaDelta":20,"acDelta":25,"focusSpellName":"","deltasDetail":{"hpDelta":40,"manaDelta":20,"acDelta":25,"svAllDelta":50,"svDeltasByType":{"FR":3,"CR":3,"MR":18,"DR":18,"PR":8}}},{"char_id":"22078217","name":"Destroyah","class_name":"Wizard","slotId":17,"slotName":"Chest","currentItemId":15788,"currentItemName":"Arantir's Robe of Discovery","itemId":26604,"itemName":"Koadic's Robe of Heightened Focus","scoreDelta":0.009874557783018868,"isUpgrade":true,"eligible":true,"hpDelta":40,"manaDelta":20,"acDelta":25,"focusSpellName":"","deltasDetail":{"hpDelta":40,"manaDelta":20,"acDelta":25,"svAllDelta":50,"svDeltasByType":{"FR":10,"CR":6,"MR":12,"DR":10,"PR":12}}},{"char_id":"Breaks","name":"Breaks","class_name":"Enchanter","slotId":17,"slotName":"Chest","currentItemId":15779,"currentItemName":"Silken Augmenter's Robe","itemId":26604,"itemName":"Koadic's Robe of Heightened Focus","scoreDelta":0.009874557783018868,"isUpgrade":true,"eligible":true,"hpDelta":40,"manaDelta":20,"acDelta":25,"focusSpellName":"","deltasDetail":{"hpDelta":40,"manaDelta":20,"acDelta":25,"svAllDelta":50,"svDeltasByType":{"FR":3,"CR":3,"MR":18,"DR":18,"PR":8}}},{"char_id":"22081257","name":"Eleander","class_name":"Enchanter","slotId":17,"slotName":"Chest","currentItemId":15779,"currentItemName":"Silken Augmenter's Robe","itemId":26604,"itemName":"Koadic's Robe of Heightened Focus","scoreDelta":0.009874557783018868,"isUpgrade":true,"eligible":true,"hpDelta":40,"manaDelta":20,"acDelta":25,"focusSpellName":"","deltasDetail":{"hpDelta":40,"manaDelta":20,"acDelta":25,"svAllDelta":50,"svDeltasByType":{"FR":3,"CR":3,"MR":18,"DR":18,"PR":8}}},{"char_id":"22078218","name":"Scorch","class_name":"Magician","slotId":17,"slotName":"Chest","currentItemId":15782,"currentItemName":"Elemental Shroud of the Prime","itemId":26604,"itemName":"Koadic's Robe of Heightened Focus","scoreDelta":0.009874557783018868,"isUpgrade":true,"eligible":true,"hpDelta":40,"manaDelta":20,"acDelta":25,"focusSpellName":"","deltasDetail":{"hpDelta":40,"manaDelta":20,"acDelta":25,"svAllDelta":50,"svDeltasByType":{"FR":6,"CR":18,"MR":6,"DR":10,"PR":10}}},{"char_id":"22081514","name":"Darco","class_name":"Enchanter","slotId":17,"slotName":"Chest","currentItemId":15779,"currentItemName":"Silken Augmenter's Robe","itemId":26604,"itemName":"Koadic's Robe of Heightened Focus","scoreDelta":0.009874557783018868,"isUpgrade":true,"eligible":true,"hpDelta":40,"manaDelta":20,"acDelta":25,"focusSpellName":"","deltasDetail":{"hpDelta":40,"manaDelta":20,"acDelta":25,"svAllDelta":50,"svDeltasByType":{"FR":3,"CR":3,"MR":18,"DR":18,"PR":8}}},{"char_id":"Estragon","name":"Estragon","class_name":"Enchanter","slotId":17,"slotName":"Chest","currentItemId":15779,"currentItemName":"Silken Augmenter's Robe","itemId":26604,"itemName":"Koadic's Robe of Heightened Focus","scoreDelta":0.009874557783018868,"isUpgrade":true,"eligible":true,"hpDelta":40,"manaDelta":20,"acDelta":25,"focusSpellName":"","deltasDetail":{"hpDelta":40,"manaDelta":20,"acDelta":25,"svAllDelta":50,"svDeltasByType":{"FR":3,"CR":3,"MR":18,"DR":18,"PR":8}}},{"char_id":"21970154","name":"Hypnotist","class_name":"Enchanter","slotId":17,"slotName":"Chest","currentItemId":7924,"currentItemName":"Calamity's End","itemId":26604,"itemName":"Koadic's Robe of Heightened Focus","scoreDelta":0.00937568789308176,"isUpgrade":true,"eligible":true,"hpDelta":70,"manaDelta":20,"acDelta":12,"focusSpellName":"","deltasDetail":{"hpDelta":70,"manaDelta":20,"acDelta":12,"svAllDelta":40,"svDeltasByType":{"FR":8,"CR":8,"MR":8,"DR":8,"PR":8}}},{"char_id":"21829639","name":"Balasten","class_name":"Magician","slotId":17,"slotName":"Chest","currentItemId":7924,"currentItemName":"Calamity's End","itemId":26604,"itemName":"Koadic's Robe of Heightened Focus","scoreDelta":0.00937568789308176,"isUpgrade":true,"eligible":true,"hpDelta":70,"manaDelta":20,"acDelta":12,"focusSpellName":"","deltasDetail":{"hpDelta":70,"manaDelta":20,"acDelta":12,"svAllDelta":40,"svDeltasByType":{"FR":8,"CR":8,"MR":8,"DR":8,"PR":8}}},{"char_id":"21918024","name":"Bobobn","class_name":"Necromancer","slotId":17,"slotName":"Chest","currentItemId":7924,"currentItemName":"Calamity's End","itemId":26604,"itemName":"Koadic's Robe of Heightened Focus","scoreDelta":0.00937568789308176,"isUpgrade":true,"eligible":true,"hpDelta":70,"manaDelta":20,"acDelta":12,"focusSpellName":"","deltasDetail":{"hpDelta":70,"manaDelta":20,"acDelta":12,"svAllDelta":40,"svDeltasByType":{"FR":8,"CR":8,"MR":8,"DR":8,"PR":8}}},{"char_id":"Nautius","name":"Nautius","class_name":"Necromancer","slotId":17,"slotName":"Chest","currentItemId":7924,"currentItemName":"Calamity's End","itemId":26604,"itemName":"Koadic's Robe of Heightened Focus","scoreDelta":0.00937568789308176,"isUpgrade":true,"eligible":true,"hpDelta":70,"manaDelta":20,"acDelta":12,"focusSpellName":"","deltasDetail":{"hpDelta":70,"manaDelta":20,"acDelta":12,"svAllDelta":40,"svDeltasByType":{"FR":8,"CR":8,"MR":8,"DR":8,"PR":8}}},{"char_id":"22081402","name":"Whiffee","class_name":"Magician","slotId":17,"slotName":"Chest","currentItemId":7924,"currentItemName":"Calamity's End","itemId":26604,"itemName":"Koadic's Robe of Heightened Focus","scoreDelta":0.00937568789308176,"isUpgrade":true,"eligible":true,"hpDelta":70,"manaDelta":20,"acDelta":12,"focusSpellName":"","deltasDetail":{"hpDelta":70,"manaDelta":20,"acDelta":12,"svAllDelta":40,"svDeltasByType":{"FR":8,"CR":8,"MR":8,"DR":8,"PR":8}}},{"char_id":"21808678","name":"Ruckus","class_name":"Magician","slotId":17,"slotName":"Chest","currentItemId":1552,"currentItemName":"Robe of Inspiration","itemId":26604,"itemName":"Koadic's Robe of Heightened Focus","scoreDelta":0.008483981918238993,"isUpgrade":true,"eligible":true,"hpDelta":120,"manaDelta":20,"acDelta":20,"focusSpellName":"","deltasDetail":{"hpDelta":120,"manaDelta":20,"acDelta":20,"svAllDelta":15,"svDeltasByType":{"FR":3,"CR":3,"MR":3,"DR":3,"PR":3}}},{"char_id":"21701442","name":"Holle","class_name":"Enchanter","slotId":17,"slotName":"Chest","currentItemId":1552,"currentItemName":"Robe of Inspiration","itemId":26604,"itemName":"Koadic's Robe of Heightened Focus","scoreDelta":0.008483981918238993,"isUpgrade":true,"eligible":true,"hpDelta":120,"manaDelta":20,"acDelta":20,"focusSpellName":"","deltasDetail":{"hpDelta":120,"manaDelta":20,"acDelta":20,"svAllDelta":15,"svDeltasByType":{"FR":3,"CR":3,"MR":3,"DR":3,"PR":3}}},{"char_id":"Inferno","name":"Inferno","class_name":"Wizard","slotId":17,"slotName":"Chest","currentItemId":1552,"currentItemName":"Robe of Inspiration","itemId":26604,"itemName":"Koadic's Robe of Heightened Focus","scoreDelta":0.008483981918238993,"isUpgrade":true,"eligible":true,"hpDelta":120,"manaDelta":20,"acDelta":20,"focusSpellName":"","deltasDetail":{"hpDelta":120,"manaDelta":20,"acDelta":20,"svAllDelta":15,"svDeltasByType":{"FR":3,"CR":3,"MR":3,"DR":3,"PR":3}}},{"char_id":"22025115","name":"Shizo","class_name":"Magician","slotId":17,"slotName":"Chest","currentItemId":1552,"currentItemName":"Robe of Inspiration","itemId":26604,"itemName":"Koadic's Robe of Heightened Focus","scoreDelta":0.008483981918238993,"isUpgrade":true,"eligible":true,"hpDelta":120,"manaDelta":20,"acDelta":20,"focusSpellName":"","deltasDetail":{"hpDelta":120,"manaDelta":20,"acDelta":20,"svAllDelta":15,"svDeltasByType":{"FR":3,"CR":3,"MR":3,"DR":3,"PR":3}}},{"char_id":"21912946","name":"Borat","class_name":"Wizard","slotId":17,"slotName":"Chest","currentItemId":10845,"currentItemName":"Robe of the Azure Sky","itemId":26604,"itemName":"Koadic's Robe of Heightened Focus","scoreDelta":0.005098565251572325,"isUpgrade":true,"eligible":true,"hpDelta":35,"manaDelta":20,"acDelta":22,"focusSpellName":"","deltasDetail":{"hpDelta":35,"manaDelta":20,"acDelta":22,"svAllDelta":15,"svDeltasByType":{"FR":3,"CR":3,"MR":3,"DR":3,"PR":3}}},{"char_id":"22008294","name":"Xelaw","class_name":"Enchanter","slotId":17,"slotName":"Chest","currentItemId":10845,"currentItemName":"Robe of the Azure Sky","itemId":26604,"itemName":"Koadic's Robe of Heightened Focus","scoreDelta":0.005098565251572325,"isUpgrade":true,"eligible":true,"hpDelta":35,"manaDelta":20,"acDelta":22,"focusSpellName":"","deltasDetail":{"hpDelta":35,"manaDelta":20,"acDelta":22,"svAllDelta":15,"svDeltasByType":{"FR":3,"CR":3,"MR":3,"DR":3,"PR":3}}},{"char_id":"21988171","name":"Senelen","class_name":"Magician","slotId":17,"slotName":"Chest","currentItemId":10845,"currentItemName":"Robe of the Azure Sky","itemId":26604,"itemName":"Koadic's Robe of Heightened Focus","scoreDelta":0.005098565251572325,"isUpgrade":true,"eligible":true,"hpDelta":35,"manaDelta":20,"acDelta":22,"focusSpellName":"","deltasDetail":{"hpDelta":35,"manaDelta":20,"acDelta":22,"svAllDelta":15,"svDeltasByType":{"FR":3,"CR":3,"MR":3,"DR":3,"PR":3}}},{"char_id":"22081401","name":"Funkee","class_name":"Enchanter","slotId":17,"slotName":"Chest","currentItemId":10845,"currentItemName":"Robe of the Azure Sky","itemId":26604,"itemName":"Koadic's Robe of Heightened Focus","scoreDelta":0.005098565251572325,"isUpgrade":true,"eligible":true,"hpDelta":35,"manaDelta":20,"acDelta":22,"focusSpellName":"","deltasDetail":{"hpDelta":35,"manaDelta":20,"acDelta":22,"svAllDelta":15,"svDeltasByType":{"FR":3,"CR":3,"MR":3,"DR":3,"PR":3}}},{"char_id":"22035857","name":"Fishsticks","class_name":"Wizard","slotId":17,"slotName":"Chest","currentItemId":10845,"currentItemName":"Robe of the Azure Sky","itemId":26604,"itemName":"Koadic's Robe of Heightened Focus","scoreDelta":0.005098565251572325,"isUpgrade":true,"eligible":true,"hpDelta":35,"manaDelta":20,"acDelta":22,"focusSpellName":"","deltasDetail":{"hpDelta":35,"manaDelta":20,"acDelta":22,"svAllDelta":15,"svDeltasByType":{"FR":3,"CR":3,"MR":3,"DR":3,"PR":3}}},{"char_id":"22032677","name":"Wizo","class_name":"Wizard","slotId":17,"slotName":"Chest","currentItemId":28910,"currentItemName":"Robe of Luring Shadows","itemId":26604,"itemName":"Koadic's Robe of Heightened Focus","scoreDelta":0.003913669418238994,"isUpgrade":true,"eligible":true,"hpDelta":20,"manaDelta":20,"acDelta":5,"focusSpellName":"","deltasDetail":{"hpDelta":20,"manaDelta":20,"acDelta":5,"svAllDelta":15,"svDeltasByType":{"FR":3,"CR":3,"MR":3,"DR":3,"PR":3}}},{"char_id":"22080766","name":"Shibi","class_name":"Wizard","slotId":17,"slotName":"Chest","currentItemId":28910,"currentItemName":"Robe of Luring Shadows","itemId":26604,"itemName":"Koadic's Robe of Heightened Focus","scoreDelta":0.003913669418238994,"isUpgrade":true,"eligible":true,"hpDelta":20,"manaDelta":20,"acDelta":5,"focusSpellName":"","deltasDetail":{"hpDelta":20,"manaDelta":20,"acDelta":5,"svAllDelta":15,"svDeltasByType":{"FR":3,"CR":3,"MR":3,"DR":3,"PR":3}}},{"char_id":"21810460","name":"Okay","class_name":"Wizard","slotId":17,"slotName":"Chest","currentItemId":28910,"currentItemName":"Robe of Luring Shadows","itemId":26604,"itemName":"Koadic's Robe of Heightened Focus","scoreDelta":0.003913669418238994,"isUpgrade":true,"eligible":true,"hpDelta":20,"manaDelta":20,"acDelta":5,"focusSpellName":"","deltasDetail":{"hpDelta":20,"manaDelta":20,"acDelta":5,"svAllDelta":15,"svDeltasByType":{"FR":3,"CR":3,"MR":3,"DR":3,"PR":3}}},{"char_id":"21897938","name":"Nilren","class_name":"Wizard","slotId":17,"slotName":"Chest","currentItemId":28910,"currentItemName":"Robe of Luring Shadows","itemId":26604,"itemName":"Koadic's Robe of Heightened Focus","scoreDelta":0.003913669418238994,"isUpgrade":true,"eligible":true,"hpDelta":20,"manaDelta":20,"acDelta":5,"focusSpellName":"","deltasDetail":{"hpDelta":20,"manaDelta":20,"acDelta":5,"svAllDelta":15,"svDeltasByType":{"FR":3,"CR":3,"MR":3,"DR":3,"PR":3}}},{"char_id":"21889836","name":"Popeye","class_name":"Enchanter","slotId":17,"slotName":"Chest","currentItemId":28910,"currentItemName":"Robe of Luring Shadows","itemId":26604,"itemName":"Koadic's Robe of Heightened Focus","scoreDelta":0.003913669418238994,"isUpgrade":true,"eligible":true,"hpDelta":20,"manaDelta":20,"acDelta":5,"focusSpellName":"","deltasDetail":{"hpDelta":20,"manaDelta":20,"acDelta":5,"svAllDelta":15,"svDeltasByType":{"FR":3,"CR":3,"MR":3,"DR":3,"PR":3}}},{"char_id":"22077678","name":"Drusella","class_name":"Wizard","slotId":17,"slotName":"Chest","currentItemId":28910,"currentItemName":"Robe of Luring Shadows","itemId":26604,"itemName":"Koadic's Robe of Heightened Focus","scoreDelta":0.003913669418238994,"isUpgrade":true,"eligible":true,"hpDelta":20,"manaDelta":20,"acDelta":5,"focusSpellName":"","deltasDetail":{"hpDelta":20,"manaDelta":20,"acDelta":5,"svAllDelta":15,"svDeltasByType":{"FR":3,"CR":3,"MR":3,"DR":3,"PR":3}}},{"char_id":"22077615","name":"Medea","class_name":"Enchanter","slotId":17,"slotName":"Chest","currentItemId":28910,"currentItemName":"Robe of Luring Shadows","itemId":26604,"itemName":"Koadic's Robe of Heightened Focus","scoreDelta":0.003913669418238994,"isUpgrade":true,"eligible":true,"hpDelta":20,"manaDelta":20,"acDelta":5,"focusSpellName":"","deltasDetail":{"hpDelta":20,"manaDelta":20,"acDelta":5,"svAllDelta":15,"svDeltasByType":{"FR":3,"CR":3,"MR":3,"DR":3,"PR":3}}},{"char_id":"22077670","name":"Selva","class_name":"Necromancer","slotId":17,"slotName":"Chest","currentItemId":28910,"currentItemName":"Robe of Luring Shadows","itemId":26604,"itemName":"Koadic's Robe of Heightened Focus","scoreDelta":0.003913669418238994,"isUpgrade":true,"eligible":true,"hpDelta":20,"manaDelta":20,"acDelta":5,"focusSpellName":"","deltasDetail":{"hpDelta":20,"manaDelta":20,"acDelta":5,"svAllDelta":15,"svDeltasByType":{"FR":3,"CR":3,"MR":3,"DR":3,"PR":3}}},{"char_id":"21962165","name":"Atar","class_name":"Magician","slotId":17,"slotName":"Chest","currentItemId":28910,"currentItemName":"Robe of Luring Shadows","itemId":26604,"itemName":"Koadic's Robe of Heightened Focus","scoreDelta":0.003913669418238994,"isUpgrade":true,"eligible":true,"hpDelta":20,"manaDelta":20,"acDelta":5,"focusSpellName":"","deltasDetail":{"hpDelta":20,"manaDelta":20,"acDelta":5,"svAllDelta":15,"svDeltasByType":{"FR":3,"CR":3,"MR":3,"DR":3,"PR":3}}},{"char_id":"21792279","name":"Yuuki","class_name":"Wizard","slotId":17,"slotName":"Chest","currentItemId":31239,"currentItemName":"Sal`Varae's Robe of Darkness","itemId":26604,"itemName":"Koadic's Robe of Heightened Focus","scoreDelta":0.0030673152515723265,"isUpgrade":true,"eligible":true,"hpDelta":20,"manaDelta":20,"acDelta":-20,"focusSpellName":"","deltasDetail":{"hpDelta":20,"manaDelta":20,"acDelta":-20,"svAllDelta":15,"svDeltasByType":{"FR":3,"CR":3,"MR":3,"DR":3,"PR":3}}},{"char_id":"22036511","name":"Iaminae","class_name":"Enchanter","slotId":17,"slotName":"Chest","currentItemId":28952,"currentItemName":"Sanguine Robe","itemId":26604,"itemName":"Koadic's Robe of Heightened Focus","scoreDelta":0.002898044418238991,"isUpgrade":true,"eligible":true,"hpDelta":-5,"manaDelta":20,"acDelta":5,"focusSpellName":"","deltasDetail":{"hpDelta":-5,"manaDelta":20,"acDelta":5,"svAllDelta":15,"svDeltasByType":{"FR":3,"CR":3,"MR":3,"DR":3,"PR":3}}},{"char_id":"22079082","name":"Phacochoerus","class_name":"Magician","slotId":17,"slotName":"Chest","currentItemId":28952,"currentItemName":"Sanguine Robe","itemId":26604,"itemName":"Koadic's Robe of Heightened Focus","scoreDelta":0.002898044418238991,"isUpgrade":true,"eligible":true,"hpDelta":-5,"manaDelta":20,"acDelta":5,"focusSpellName":"","deltasDetail":{"hpDelta":-5,"manaDelta":20,"acDelta":5,"svAllDelta":15,"svDeltasByType":{"FR":3,"CR":3,"MR":3,"DR":3,"PR":3}}},{"char_id":"Hellacious","name":"Hellacious","class_name":"Necromancer","slotId":17,"slotName":"Chest","currentItemId":28952,"currentItemName":"Sanguine Robe","itemId":26604,"itemName":"Koadic's Robe of Heightened Focus","scoreDelta":0.002898044418238991,"isUpgrade":true,"eligible":true,"hpDelta":-5,"manaDelta":20,"acDelta":5,"focusSpellName":"","deltasDetail":{"hpDelta":-5,"manaDelta":20,"acDelta":5,"svAllDelta":15,"svDeltasByType":{"FR":3,"CR":3,"MR":3,"DR":3,"PR":3}}},{"char_id":"22077595","name":"Whammo","class_name":"Wizard","slotId":17,"slotName":"Chest","currentItemId":28952,"currentItemName":"Sanguine Robe","itemId":26604,"itemName":"Koadic's Robe of Heightened Focus","scoreDelta":0.002898044418238991,"isUpgrade":true,"eligible":true,"hpDelta":-5,"manaDelta":20,"acDelta":5,"focusSpellName":"","deltasDetail":{"hpDelta":-5,"manaDelta":20,"acDelta":5,"svAllDelta":15,"svDeltasByType":{"FR":3,"CR":3,"MR":3,"DR":3,"PR":3}}},{"char_id":"21724078","name":"Bott","class_name":"Necromancer","slotId":17,"slotName":"Chest","currentItemId":28952,"currentItemName":"Sanguine Robe","itemId":26604,"itemName":"Koadic's Robe of Heightened Focus","scoreDelta":0.002898044418238991,"isUpgrade":true,"eligible":true,"hpDelta":-5,"manaDelta":20,"acDelta":5,"focusSpellName":"","deltasDetail":{"hpDelta":-5,"manaDelta":20,"acDelta":5,"svAllDelta":15,"svDeltasByType":{"FR":3,"CR":3,"MR":3,"DR":3,"PR":3}}},{"char_id":"22077716","name":"Stompa","class_name":"Enchanter","slotId":17,"slotName":"Chest","currentItemId":28952,"currentItemName":"Sanguine Robe","itemId":26604,"itemName":"Koadic's Robe of Heightened Focus","scoreDelta":0.002898044418238991,"isUpgrade":true,"eligible":true,"hpDelta":-5,"manaDelta":20,"acDelta":5,"focusSpellName":"","deltasDetail":{"hpDelta":-5,"manaDelta":20,"acDelta":5,"svAllDelta":15,"svDeltasByType":{"FR":3,"CR":3,"MR":3,"DR":3,"PR":3}}},{"char_id":"22077753","name":"Necrosis","class_name":"Necromancer","slotId":17,"slotName":"Chest","currentItemId":28952,"currentItemName":"Sanguine Robe","itemId":26604,"itemName":"Koadic's Robe of Heightened Focus","scoreDelta":0.002898044418238991,"isUpgrade":true,"eligible":true,"hpDelta":-5,"manaDelta":20,"acDelta":5,"focusSpellName":"","deltasDetail":{"hpDelta":-5,"manaDelta":20,"acDelta":5,"svAllDelta":15,"svDeltasByType":{"FR":3,"CR":3,"MR":3,"DR":3,"PR":3}}},{"char_id":"22077667","name":"Baits","class_name":"Enchanter","slotId":17,"slotName":"Chest","currentItemId":28952,"currentItemName":"Sanguine Robe","itemId":26604,"itemName":"Koadic's Robe of Heightened Focus","scoreDelta":0.002898044418238991,"isUpgrade":true,"eligible":true,"hpDelta":-5,"manaDelta":20,"acDelta":5,"focusSpellName":"","deltasDetail":{"hpDelta":-5,"manaDelta":20,"acDelta":5,"svAllDelta":15,"svDeltasByType":{"FR":3,"CR":3,"MR":3,"DR":3,"PR":3}}},{"char_id":"Minchanter","name":"Minchanter","class_name":"Enchanter","slotId":17,"slotName":"Chest","currentItemId":28952,"currentItemName":"Sanguine Robe","itemId":26604,"itemName":"Koadic's Robe of Heightened Focus","scoreDelta":0.002898044418238991,"isUpgrade":true,"eligible":true,"hpDelta":-5,"manaDelta":20,"acDelta":5,"focusSpellName":"","deltasDetail":{"hpDelta":-5,"manaDelta":20,"acDelta":5,"svAllDelta":15,"svDeltasByType":{"FR":3,"CR":3,"MR":3,"DR":3,"PR":3}}},{"char_id":"22080835","name":"Sanuuven","class_name":"Enchanter","slotId":17,"slotName":"Chest","currentItemId":28952,"currentItemName":"Sanguine Robe","itemId":26604,"itemName":"Koadic's Robe of Heightened Focus","scoreDelta":0.002898044418238991,"isUpgrade":true,"eligible":true,"hpDelta":-5,"manaDelta":20,"acDelta":5,"focusSpellName":"","deltasDetail":{"hpDelta":-5,"manaDelta":20,"acDelta":5,"svAllDelta":15,"svDeltasByType":{"FR":3,"CR":3,"MR":3,"DR":3,"PR":3}}},{"char_id":"22077698","name":"Megatron","class_name":"Enchanter","slotId":17,"slotName":"Chest","currentItemId":28952,"currentItemName":"Sanguine Robe","itemId":26604,"itemName":"Koadic's Robe of Heightened Focus","scoreDelta":0.002898044418238991,"isUpgrade":true,"eligible":true,"hpDelta":-5,"manaDelta":20,"acDelta":5,"focusSpellName":"","deltasDetail":{"hpDelta":-5,"manaDelta":20,"acDelta":5,"svAllDelta":15,"svDeltasByType":{"FR":3,"CR":3,"MR":3,"DR":3,"PR":3}}},{"char_id":"22081305","name":"Euphoria","class_name":"Magician","slotId":17,"slotName":"Chest","currentItemId":14747,"currentItemName":"Vest of Phoenix Feathers","itemId":26604,"itemName":"Koadic's Robe of Heightened Focus","scoreDelta":0.0012257763364779892,"isUpgrade":true,"eligible":true,"hpDelta":-30,"manaDelta":-30,"acDelta":4,"focusSpellName":"","deltasDetail":{"hpDelta":-30,"manaDelta":-30,"acDelta":4,"svAllDelta":30,"svDeltasByType":{"FR":18,"CR":-12,"MR":-12,"DR":18,"PR":18}}},{"char_id":"22080767","name":"Enchanta","class_name":"Enchanter","slotId":17,"slotName":"Chest","currentItemId":14747,"currentItemName":"Vest of Phoenix Feathers","itemId":26604,"itemName":"Koadic's Robe of Heightened Focus","scoreDelta":0.0012257763364779892,"isUpgrade":true,"eligible":true,"hpDelta":-30,"manaDelta":-30,"acDelta":4,"focusSpellName":"","deltasDetail":{"hpDelta":-30,"manaDelta":-30,"acDelta":4,"svAllDelta":30,"svDeltasByType":{"FR":18,"CR":-12,"MR":-12,"DR":18,"PR":18}}},{"char_id":"22034565","name":"Mind","class_name":"Enchanter","slotId":17,"slotName":"Chest","currentItemId":14747,"currentItemName":"Vest of Phoenix Feathers","itemId":26604,"itemName":"Koadic's Robe of Heightened Focus","scoreDelta":0.0012257763364779892,"isUpgrade":true,"eligible":true,"hpDelta":-30,"manaDelta":-30,"acDelta":4,"focusSpellName":"","deltasDetail":{"hpDelta":-30,"manaDelta":-30,"acDelta":4,"svAllDelta":30,"svDeltasByType":{"FR":18,"CR":-12,"MR":-12,"DR":18,"PR":18}}},{"char_id":"22077652","name":"Pistolwhip","class_name":"Magician","slotId":17,"slotName":"Chest","currentItemId":14747,"currentItemName":"Vest of Phoenix Feathers","itemId":26604,"itemName":"Koadic's Robe of Heightened Focus","scoreDelta":0.0012257763364779892,"isUpgrade":true,"eligible":true,"hpDelta":-30,"manaDelta":-30,"acDelta":4,"focusSpellName":"","deltasDetail":{"hpDelta":-30,"manaDelta":-30,"acDelta":4,"svAllDelta":30,"svDeltasByType":{"FR":18,"CR":-12,"MR":-12,"DR":18,"PR":18}}},{"char_id":"Merfan","name":"Merfan","class_name":"Enchanter","slotId":17,"slotName":"Chest","currentItemId":14747,"currentItemName":"Vest of Phoenix Feathers","itemId":26604,"itemName":"Koadic's Robe of Heightened Focus","scoreDelta":0.0012257763364779892,"isUpgrade":true,"eligible":true,"hpDelta":-30,"manaDelta":-30,"acDelta":4,"focusSpellName":"","deltasDetail":{"hpDelta":-30,"manaDelta":-30,"acDelta":4,"svAllDelta":30,"svDeltasByType":{"FR":18,"CR":-12,"MR":-12,"DR":18,"PR":18}}},{"char_id":"Srik","name":"Srik","class_name":"Enchanter","slotId":17,"slotName":"Chest","currentItemId":14747,"currentItemName":"Vest of Phoenix Feathers","itemId":26604,"itemName":"Koadic's Robe of Heightened Focus","scoreDelta":0.0012257763364779892,"isUpgrade":true,"eligible":true,"hpDelta":-30,"manaDelta":-30,"acDelta":4,"focusSpellName":"","deltasDetail":{"hpDelta":-30,"manaDelta":-30,"acDelta":4,"svAllDelta":30,"svDeltasByType":{"FR":18,"CR":-12,"MR":-12,"DR":18,"PR":18}}}]}