{"version":1,"itemId":"28882","generated_at":"2026-04-12T18:59:36.919Z","activity_days":120,"entries":[{"char_id":"22080826","name":"Threllin","class_name":"Warrior","slotId":7,"slotName":"Arms","currentItemId":30524,"currentItemName":"Ebony Armguards","itemId":28882,"itemName":"Steel Skin Armplates","scoreDelta":0.015014240790655886,"isUpgrade":true,"eligible":true,"hpDelta":85,"manaDelta":85,"acDelta":40,"focusSpellName":"","deltasDetail":{"hpDelta":85,"manaDelta":85,"acDelta":40,"svAllDelta":35,"svDeltasByType":{"FR":7,"CR":7,"MR":7,"DR":7,"PR":7}}}]}